{
  "9adc3185-b027-4d8f-8a63-9ceb009fa3c7": {
    "source_ip": [
      "节点18-cdma_0",
      "节点18-cdma_1"
    ],
    "target_ip": [
      "节点3-ddr_0",
      "节点3-ddr_1",
      "节点7-ddr_0",
      "节点7-ddr_1",
      "节点11-ddr_0",
      "节点11-ddr_1",
      "节点15-ddr_0",
      "节点15-ddr_1"
    ],
    "speed_gbps": 50.4,
    "burst_length": 4,
    "request_type": "W",
    "end_time_ns": 300,
    "id": "9adc3185-b027-4d8f-8a63-9ceb009fa3c7",
    "topology": "5x4",
    "mode": "dcin",
    "created_at": "2025-11-27T23:21:06.325081",
    "source_die": null,
    "target_die": null,
    "die_pairs": [
      [
        3,
        3
      ]
    ]
  }
}